Metadata-Version: 1.0
Name: Ege2021naizi
Version: 0.1.1
Summary: Ege po informatike na izi
Home-page: UNKNOWN
Author: UNKNOWN
Author-email: gta5kostya@mail.ru
License: UNKNOWN
Platform: UNKNOWN
